nonebot_plugin_wordle_help/__init__.py
nonebot_plugin_wordle_help/data.json
nonebot_plugin_wordle_help/handle.py
nonebot_plugin_wordle_help-0.0.3.dist-info/LICENSE
nonebot_plugin_wordle_help-0.0.3.dist-info/METADATA
nonebot_plugin_wordle_help-0.0.3.dist-info/WHEEL
nonebot_plugin_wordle_help-0.0.3.dist-info/top_level.txt
nonebot_plugin_wordle_help-0.0.3.dist-info/RECORD
