Metadata-Version: 2.1
Name: nonebot-plugin-wordle-help
Version: 0.0.3
Summary: wordle小游戏工具
Home-page: https://github.com/Special-Week/Hinata-Bot/tree/main/src/plugins/wordle_help
Author: Special-Week
Author-email: 2385612749@qq.com
Requires-Python: >=3.8.0
License-File: LICENSE
Requires-Dist: nonebot2
Requires-Dist: nonebot-adapter-onebot
